toyaikit/__init__.py
toyaikit/__version__.py
toyaikit/llm.py
toyaikit/main.py
toyaikit/pricing.py
toyaikit/tools.py
toyaikit/utils.py
toyaikit/chat/__init__.py
toyaikit/chat/chat.py
toyaikit/chat/interface.py
toyaikit/chat/runners.py
toyaikit/mcp/__init__.py
toyaikit/mcp/client.py
toyaikit/mcp/mcp_tools.py
toyaikit/mcp/transport.py
toyaikit-0.0.9.dist-info/METADATA
toyaikit-0.0.9.dist-info/WHEEL
toyaikit-0.0.9.dist-info/RECORD
