Metadata-Version: 2.4
Name: toyaikit
Version: 0.0.9
Summary: Toolkit for building AI assistants and tool integrations.
Project-URL: Homepage, https://github.com/alexeygrigorev/toyaikit
Project-URL: Repository, https://github.com/alexeygrigorev/toyaikit
Project-URL: Issues, https://github.com/alexeygrigorev/toyaikit/issues
Author-email: Alexey Grigorev <alexey@datatalks.club>
Maintainer-email: Alexey Grigorev <alexey@datatalks.club>
License: WTFPL
Keywords: ai,assistant,integration,tools
Classifier: Development Status :: 3 - Alpha
Classifier: Intended Audience :: Developers
Classifier: License :: Other/Proprietary License
Classifier: Programming Language :: Python :: 3
Classifier: Programming Language :: Python :: 3.10
Classifier: Programming Language :: Python :: 3.11
Classifier: Programming Language :: Python :: 3.12
Classifier: Programming Language :: Python :: 3.13
Classifier: Topic :: Software Development :: Libraries :: Python Modules
Requires-Python: >=3.10
Requires-Dist: anthropic>=0.40.0
Requires-Dist: genai-prices>=0.0.34
Requires-Dist: ipython
Requires-Dist: mistune>=3.1.3
Requires-Dist: openai>=1.97.0
